Metadata-Version: 2.1
Name: django4-bootstrap-breadcrumbs
Version: 0.10.0
Summary: Django breadcrumbs for Bootstrap 2, 3 or 4
Home-page: https://github.com/fleonasb/django4-bootstrap-breadcrumbs
Author: Fidel Leon
Author-email: fleon@asbarcelona.com
License: MIT
Platform: any
Classifier: License :: OSI Approved :: MIT License
Classifier: Intended Audience :: Developers
Classifier: Programming Language :: Python :: 2
Classifier: Programming Language :: Python :: 3
Classifier: Topic :: Software Development :: Libraries :: Python Modules
License-File: LICENSE
Requires-Dist: six
